detime/__init__.py
detime/test_fmap.py
detime-1.1.9.dist-info/METADATA
detime-1.1.9.dist-info/WHEEL
detime-1.1.9.dist-info/entry_points.txt
detime-1.1.9.dist-info/top_level.txt
detime-1.1.9.dist-info/RECORD
