Metadata-Version: 2.1
Name: detime
Version: 1.1.9
Summary: Decimal Silicon Time: time since UNIX zero, in decimal.
Home-page: https://github.com/mindey/detime
Author: Mindey
Author-email: ~@mindey.com
License: MIT
Platform: UNKNOWN
Provides-Extra: test
Requires-Dist: coverage ; extra == 'test'
Requires-Dist: pytest ; extra == 'test'
Requires-Dist: pytest-cov ; extra == 'test'
